npaes/__init__.py
npaes-0.3.dist-info/LICENSE
npaes-0.3.dist-info/METADATA
npaes-0.3.dist-info/WHEEL
npaes-0.3.dist-info/top_level.txt
npaes-0.3.dist-info/RECORD
