Metadata-Version: 2.1
Name: npaes
Version: 0.3
Summary: Advanced Encryption Standard (AES) NumPy implementation
Home-page: https://github.com/bsolomon1124/npaes
Author: Brad Solomon
Author-email: brad.solomon.1124@gmail.com
License: Apache 2.0
Keywords: aes,aes-128,aes-192,aes-256,aes 128,aes 192,aes 256,encryption,decryption,numpy,symmetric,cipher
Platform: UNKNOWN
Classifier: Development Status :: 2 - Pre-Alpha
Classifier: Topic :: Security :: Cryptography
Classifier: License :: OSI Approved :: Apache Software License
Classifier: Programming Language :: Python :: 2
Classifier: Programming Language :: Python :: 2.7
Classifier: Programming Language :: Python :: 3
Classifier: Programming Language :: Python :: 3.5
Classifier: Programming Language :: Python :: 3.6
Classifier: Programming Language :: Python :: 3.7
Classifier: Programming Language :: Python :: Implementation :: CPython
Requires-Dist: numpy (<=1.16,>=1.14.6)
Requires-Dist: setuptools
